uniform/__init__.py
uniform/__version__.py
uniform-0.2.2.data/data/LICENSE
uniform-0.2.2.dist-info/LICENSE
uniform-0.2.2.dist-info/METADATA
uniform-0.2.2.dist-info/WHEEL
uniform-0.2.2.dist-info/top_level.txt
uniform-0.2.2.dist-info/RECORD
