Metadata-Version: 2.1
Name: uniform
Version: 0.2.2
Summary: Uniform - dress your form processing endpoints📋
Home-page: https://gitlab.com/not-good-igor/uniform.py
Author: Igor Nehoroshev
Author-email: mail@neigor.me
License: Unlicense
Platform: UNKNOWN
Classifier: Development Status :: 3 - Alpha
Classifier: Environment :: Web Environment
Classifier: Intended Audience :: Developers
Classifier: License :: Public Domain
Classifier: Operating System :: OS Independent
Classifier: Programming Language :: Python :: 3
Classifier: Programming Language :: Python :: 3.6
Classifier: Programming Language :: Python :: 3.7
Classifier: Programming Language :: Python :: 3.8
Requires-Python: >=3.6
Requires-Dist: typesystem
Requires-Dist: starlette
Provides-Extra: docs
Requires-Dist: mkdocs ; extra == 'docs'
Requires-Dist: mkdocs-material ; extra == 'docs'
Provides-Extra: lint
Requires-Dist: mypy ; extra == 'lint'
Requires-Dist: autoflake ; extra == 'lint'
Requires-Dist: black ; extra == 'lint'
Requires-Dist: isort ; extra == 'lint'
Provides-Extra: test
Requires-Dist: asynctest ; extra == 'test'
Requires-Dist: httpx ; extra == 'test'
Requires-Dist: coverage ; extra == 'test'
Requires-Dist: python-multipart ; extra == 'test'
